CHANGES.rst
CONTRIBUTORS.rst
MANIFEST.in
README.rst
setup.cfg
setup.py
docs/LICENSE.GPL
docs/LICENSE.rst
docs/index.rst
src/imio/__init__.py
src/imio.project.policy.egg-info/PKG-INFO
src/imio.project.policy.egg-info/SOURCES.txt
src/imio.project.policy.egg-info/dependency_links.txt
src/imio.project.policy.egg-info/entry_points.txt
src/imio.project.policy.egg-info/namespace_packages.txt
src/imio.project.policy.egg-info/not-zip-safe
src/imio.project.policy.egg-info/requires.txt
src/imio.project.policy.egg-info/top_level.txt
src/imio/project/__init__.py
src/imio/project/policy/__init__.py
src/imio/project/policy/configure.zcml