Metadata-Version: 1.1
Name: imio.project.policy
Version: 1.1
Summary: Policy for project environment
Home-page: https://pypi.python.org/pypi/imio.project.policy
Author: Stephan Geulette
Author-email: support@imio.be
License: GPL version 2
Keywords: Python Plone
Platform: UNKNOWN
Classifier: Environment :: Web Environment
Classifier: Framework :: Plone
Classifier: Framework :: Plone :: 4.3
Classifier: Programming Language :: Python
Classifier: Programming Language :: Python :: 2.7
Classifier: Operating System :: OS Independent
Classifier: License :: OSI Approved :: GNU General Public License v2 (GPLv2)
